Metadata-Version: 2.1
Name: ICPOptimize
Version: 2.4
Summary: Python 3 Implementation of ICP and ICPRE
Home-page: https://github.com/nicholastoddsmith/ICPOptimize
Author: Nicholas T. Smith
Author-email: nicholastsmithblog@gmail.com
License: UNKNOWN
Keywords: optimization,optimizer,linear,ICP,ICPRE
Platform: UNKNOWN
Classifier: Intended Audience :: Education
Classifier: Intended Audience :: Science/Research
Classifier: Topic :: Scientific/Engineering
Classifier: Topic :: Scientific/Engineering :: Mathematics
Classifier: Natural Language :: English
Classifier: Operating System :: OS Independent
Classifier: Programming Language :: C
Classifier: Programming Language :: Cython
Classifier: Programming Language :: Python
Classifier: Programming Language :: Python :: 3
License-File: LICENSE
